{
  "custom_id": "III-5-C-22--V-1_page0405",
  "page": 405,
  "language": "unknown",
  "orientation": "normal",
  "body_text": "In the Turkı collectanea of G. Raquette¹ I note the following Chinese words:\n*čiñ-sāy*, celery, from *č'in ts'ai* 芹菜.\n*manto*, meat-dumpling, from *man-t'ou* 饅頭.\n*čizŭ*, a Chinese foot (measure), from *č'i-tse* 尺子.\n*lobo*, a long turnip, from *lo-po* 蘿蔔.\n*jin*, a Chinese pound, from *čin* 斤.\n\nA few other remarks on Turkı words recorded by Le Coq may follow here:\n*nāhāl* (\"ruby\") is apparently Persian *lāl* (above, p. 575).\n*zummurāt* (\"emerald\") is not Arabic-Turkish, but Persian (above, p. 519).\nThere is no reason to question the Persian origin of *palas* (\"cloth, sail\"); it is identical with Persian *bālās* (above, p. 495).\n*dōwā* (\"hill\") is identical with Turkish *deve*, *teve* (\"camel\"); cf. *T'oung Pao*, 1915, p. 21.\n*yilpis* (\"snow-leopard\") is identical with Mongol *irbis* (\"panther\").",
  "captions": [],
  "footnotes": [
    "¹ Eastern Turki Grammar, *Mitt. Sem. Or. Spr.*, 1914, II, pp. 170–232."
  ],
  "headers": "Chinese Elements in Turki 579",
  "parse_error": false
}